jsonrpcbase/__init__.py
jsonrpcbase/exceptions.py
jsonrpcbase/main.py
jsonrpcbase/types.py
jsonrpcbase/utils.py
kbase_jsonrpcbase-0.3.0a6.dist-info/LICENSE
kbase_jsonrpcbase-0.3.0a6.dist-info/WHEEL
kbase_jsonrpcbase-0.3.0a6.dist-info/METADATA
kbase_jsonrpcbase-0.3.0a6.dist-info/RECORD
